flet_ads/__init__.py
flet_ads/banner_ad.py
flet_ads/base_ad.py
flet_ads/interstitial_ad.py
flet_ads/native_ad.py
flet_ads/types.py
flet_ads-0.80.5.dist-info/licenses/LICENSE
flutter/flet_ads/analysis_options.yaml
flutter/flet_ads/pubspec.lock
flutter/flet_ads/pubspec.yaml
flutter/flet_ads/lib/flet_ads.dart
flutter/flet_ads/lib/src/banner.dart
flutter/flet_ads/lib/src/extension.dart
flutter/flet_ads/lib/src/interstitial.dart
flutter/flet_ads/lib/src/native.dart
flutter/flet_ads/lib/utils/ads.dart
flutter/flet_ads/lib/utils/native.dart
flet_ads-0.80.5.dist-info/METADATA
flet_ads-0.80.5.dist-info/WHEEL
flet_ads-0.80.5.dist-info/top_level.txt
flet_ads-0.80.5.dist-info/RECORD
